{
  "type": "minecraft:ore",
  "config": {
    "size": 16,
    "discard_chance_on_air_exposure": 0,
    "targets": [
      {
        "target": {
          "predicate_type": "tag_match",
          "tag": "stone_ore_replaceables"
        },
        "state": {
          "Name": "cum:pietra_balatrante"
        }
      },
      {
        "target": {
          "predicate_type": "tag_match",
          "tag": "forge:stone"
        },
        "state": {
          "Name": "cum:pietra_balatrante"
        }
      }
    ]
  }
}